pytest_snapmock/__init__.py
pytest_snapmock/_version.py
pytest_snapmock/plugin.py
pytest_snapmock-0.0.1.dist-info/LICENSE
pytest_snapmock-0.0.1.dist-info/METADATA
pytest_snapmock-0.0.1.dist-info/WHEEL
pytest_snapmock-0.0.1.dist-info/entry_points.txt
pytest_snapmock-0.0.1.dist-info/top_level.txt
pytest_snapmock-0.0.1.dist-info/RECORD
