Metadata-Version: 2.1
Name: pytest-snapmock
Version: 0.0.1
Summary: Snapshots for your mocks.
Author-email: Richard Postelnik <richard.postelnik@gmail.com>
Maintainer-email: Richard Postelnik <richard.postelnik@gmail.com>
Classifier: Framework :: Pytest
Classifier: Programming Language :: Python :: 3
Classifier: Programming Language :: Python :: 3.7
Classifier: Programming Language :: Python :: 3.8
Classifier: Programming Language :: Python :: 3.9
Classifier: Programming Language :: Python :: 3.10
Classifier: Programming Language :: Python :: 3.11
Classifier: Programming Language :: Python :: 3.12
Classifier: Operating System :: OS Independent
Classifier: License :: OSI Approved :: MIT License
Requires-Python: >=3.7
License-File: LICENSE
